systime_stackapi/__init__.py
systime_stackapi/authenticator.py
systime_stackapi/backupService.py
systime_stackapi/exceptions.py
systime_stackapi/highlevelStackService.py
systime_stackapi/isbnRegister.py
systime_stackapi/stackDiscovery.py
systime_stackapi/stackService.py
systime_stackapi/taskRegister.py
systime_stackapi/test.py
systime_stackapi/cli/__init__.py
systime_stackapi/cli/stackcli.py
systime_stackapi/cli/commands/__init__.py
systime_stackapi/cli/commands/cmd_list-installations.py
systime_stackapi/cli/commands/cmd_setup-db-connection.py
systime_stackapi/cli/commands/cmd_show-installation.py
systime_stackapi/cli/commands/cmd_typo3config.py
systime_stackapi-0.0.43.dist-info/LICENSE
systime_stackapi-0.0.43.dist-info/METADATA
systime_stackapi-0.0.43.dist-info/WHEEL
systime_stackapi-0.0.43.dist-info/entry_points.txt
systime_stackapi-0.0.43.dist-info/top_level.txt
systime_stackapi-0.0.43.dist-info/RECORD
