Metadata-Version: 2.1
Name: systime-stackapi
Version: 0.0.43
Summary: A python API for accessing Systimes infrastructure services.
Home-page: https://bitbucket.org/systime/systime-stack-python-api
Author: Rasmus Larsen
Author-email: rla@systime.dk
Classifier: Development Status :: 3 - Alpha
Classifier: Programming Language :: Python :: 3
Classifier: License :: OSI Approved :: MIT License
Classifier: Operating System :: OS Independent
License-File: LICENSE
Requires-Dist: requests >=2.22.0
Requires-Dist: dnspython >=1.15.0
Requires-Dist: PyJWT >=2.0.0
Requires-Dist: Click >=7.0
Requires-Dist: fcache >=0.4.7
Requires-Dist: Brotli >=1.0.9
